sql_via_code/__init__.py
sql_via_code/engine_manager.py
sql_via_code/logger_config.py
sql_via_code/sql_via_code.py
sql_via_code-0.3.6.dist-info/METADATA
sql_via_code-0.3.6.dist-info/WHEEL
sql_via_code-0.3.6.dist-info/top_level.txt
sql_via_code-0.3.6.dist-info/RECORD
