Metadata-Version: 2.1
Name: sql_via_code
Version: 0.3.6
Summary: A Python package to execute SQL queries and procedures and manage backups.
Author: Afik Ratzon
Author-email: afik.ratzon@gmail.com
Classifier: Programming Language :: Python :: 3
Classifier: License :: OSI Approved :: MIT License
Classifier: Operating System :: OS Independent
Requires-Python: >=3.6
Requires-Dist: aiofiles==24.1.0
Requires-Dist: aiomysql==0.2.0
Requires-Dist: aioodbc==0.5.0
Requires-Dist: aiosqlite==0.20.0
Requires-Dist: asyncpg==0.30.0
Requires-Dist: backports.tarfile==1.2.0
Requires-Dist: build==1.2.2.post1
Requires-Dist: certifi==2024.8.30
Requires-Dist: cffi==1.17.1
Requires-Dist: charset-normalizer==3.4.0
Requires-Dist: colorama==0.4.6
Requires-Dist: cryptography==44.0.0
Requires-Dist: docutils==0.21.2
Requires-Dist: greenlet==3.1.1
Requires-Dist: idna==3.10
Requires-Dist: importlib_metadata==8.5.0
Requires-Dist: iniconfig==2.0.0
Requires-Dist: jaraco.classes==3.4.0
Requires-Dist: jaraco.context==6.0.1
Requires-Dist: jaraco.functools==4.1.0
Requires-Dist: keyring==25.5.0
Requires-Dist: markdown-it-py==3.0.0
Requires-Dist: mdurl==0.1.2
Requires-Dist: more-itertools==10.5.0
Requires-Dist: nh3==0.2.19
Requires-Dist: numpy==2.1.3
Requires-Dist: oracledb==2.5.1
Requires-Dist: packaging==24.2
Requires-Dist: pandas==2.2.3
Requires-Dist: pkginfo==1.11.2
Requires-Dist: pluggy==1.5.0
Requires-Dist: pycparser==2.22
Requires-Dist: Pygments==2.18.0
Requires-Dist: PyMySQL==1.1.1
Requires-Dist: pyodbc==5.2.0
Requires-Dist: pyproject_hooks==1.2.0
Requires-Dist: pytest==8.3.4
Requires-Dist: pytest-asyncio==0.24.0
Requires-Dist: python-dateutil==2.9.0.post0
Requires-Dist: python-dotenv==1.0.1
Requires-Dist: pytz==2024.2
Requires-Dist: pywin32-ctypes==0.2.3
Requires-Dist: readme_renderer==44.0
Requires-Dist: requests==2.32.3
Requires-Dist: requests-toolbelt==1.0.0
Requires-Dist: rfc3986==2.0.0
Requires-Dist: rich==13.9.4
Requires-Dist: setuptools==75.6.0
Requires-Dist: six==1.16.0
Requires-Dist: SQLAlchemy==2.0.36
Requires-Dist: tabulate==0.9.0
Requires-Dist: twine==6.0.1
Requires-Dist: typing_extensions==4.12.2
Requires-Dist: tzdata==2024.2
Requires-Dist: urllib3==2.2.3
Requires-Dist: wheel==0.45.1
Requires-Dist: zipp==3.21.0
